{
    "name": "SysUserRole",
    "fields": [
        {
            "fieldName": "userId",
            "fieldType": "String"
        },
        {
            "fieldName": "roleId",
            "fieldType": "String"
        },
        {
            "fieldName": "createTime",
            "fieldType": "Instant"
        },
        {
            "fieldName": "updateTime",
            "fieldType": "Instant"
        }
    ],
    "relationships": [],
    "changelogDate": "20191121062625",
    "entityTableName": "sys_user_role",
    "dto": "no",
    "pagination": "no",
    "service": "no",
    "jpaMetamodelFiltering": false,
    "fluentMethods": true,
    "readOnly": false,
    "clientRootFolder": "",
    "applications": "*"
}